betalibpy/__init__.py
betalibpy/networking.py
betalibpy-0.0.1.dist-info/LICENSE
betalibpy-0.0.1.dist-info/METADATA
betalibpy-0.0.1.dist-info/WHEEL
betalibpy-0.0.1.dist-info/top_level.txt
betalibpy-0.0.1.dist-info/RECORD
