Metadata-Version: 2.1
Name: betalibpy
Version: 0.0.1
Summary: An assortment of Python modules to make life easier.
Home-page: https://github.com/BetaPictoris/betalibpy
Author: Beta Pictoris
Author-email: mrhallway@protonmail.com
License: UNKNOWN
Project-URL: Bug Tracker, https://github.com/BetaPictoris/betalibpy/issues
Platform: UNKNOWN
Classifier: Programming Language :: Python :: 3
Classifier: License :: OSI Approved :: MIT License
Classifier: Operating System :: OS Independent
Requires-Python: >=3.6
License-File: LICENSE
